PySide6ElaWidgetTools/ElaWidgetTools.abi3.so
PySide6ElaWidgetTools/ElaWidgetTools.pyi
PySide6ElaWidgetTools/__init__.py
pyside6_elawidgettools-0.7.4.dist-info/METADATA
pyside6_elawidgettools-0.7.4.dist-info/WHEEL
pyside6_elawidgettools-0.7.4.dist-info/top_level.txt
pyside6_elawidgettools-0.7.4.dist-info/RECORD
